lava/__init__.py
lava/buffer.py
lava/session.py
lava/shader.py
lava/util.py
lava/api/__init__.py
lava/api/bytes.py
lava/api/device.py
lava/api/instance.py
lava/api/memory.py
lava/api/pipeline.py
lava/api/shader.py
lava/api/util.py
lava/api/vulkan.py
lava/api/bytecode/__init__.py
lava/api/bytecode/logical.py
lava/api/bytecode/physical.py
lava/api/constants/__init__.py
lava/api/constants/spirv.py
lava/api/constants/vk.py
lava-0.4.1.dist-info/METADATA
lava-0.4.1.dist-info/WHEEL
lava-0.4.1.dist-info/top_level.txt
lava-0.4.1.dist-info/RECORD
