Metadata-Version: 2.1
Name: lava
Version: 0.4.1
Summary: Highlevel Wrapper for Vulkan's Compute API
Home-page: https://github.com/osanj/lava
Author: Jonas Schuepfer
Author-email: jonasschuepfer@gmail.com
License: UNKNOWN
Keywords: Vulkan,Parallel Computing,Numpy
Platform: UNKNOWN
Requires-Dist: future
Requires-Dist: numpy
Requires-Dist: vulkan
